{
  "annotations": {
    "list": [
      {
        "builtIn": 0,
        "datasource": { "type": "prometheus", "uid": "${datasource_prometheus}" },
        "enable": true,
        "expr": "count(ALERTS{alertstate=\"firing\"}) > 0",
        "hide": false,
        "iconColor": "red",
        "name": "Firing Alerts",
        "showIn": 0,
        "textFormat": "{{alertname}}",
        "titleFormat": "Firing Alerts",
        "type": "tags"
      }
    ]
  },
  "editable": true,
  "fiscalYearStartMonth": 0,
  "graphTooltip": 1,
  "id": null,
  "links": [
    {
      "asDropdown": true,
      "dashboards": [
        { "tags": ["graveboards"] }
      ],
      "includeVars": true,
      "keepTime": true,
      "targetBlank": false,
      "title": "Dashboards",
      "type": "dashboards"
    }
  ],
  "liveNow": false,
  "panels": [
    {
      "collapsed": false,
      "gridPos": { "h": 1, "w": 24, "x": 0, "y": 0 },
      "id": 1,
      "title": "RED KPIs",
      "type": "row"
    },
    {
      "datasource": { "type": "prometheus", "uid": "${datasource_prometheus}" },
      "fieldConfig": {
        "defaults": {
          "color": { "mode": "thresholds" },
          "thresholds": {
            "mode": "absolute",
            "steps": [
              { "color": "green", "value": null },
              { "color": "amber", "value": 1 },
              { "color": "red", "value": 5 }
            ]
          },
          "unit": "reqps"
        }
      },
      "gridPos": { "h": 4, "w": 4, "x": 0, "y": 1 },
      "id": 2,
      "options": {
        "reduceOptions": {
          "calcs": ["lastNotNull"],
          "fields": "",
          "values": false
        }
      },
      "targets": [
        {
          "expr": "job:http_requests:rate5m",
          "legendFormat": "Rate",
          "refId": "A"
        }
      ],
      "title": "Request Rate",
      "description": "Total requests per second over the last 5 minutes.",
      "type": "stat"
    },
    {
      "datasource": { "type": "prometheus", "uid": "${datasource_prometheus}" },
      "fieldConfig": {
        "defaults": {
          "color": { "mode": "thresholds" },
          "thresholds": {
            "mode": "absolute",
            "steps": [
              { "color": "green", "value": null },
              { "color": "amber", "value": 5 },
              { "color": "red", "value": 25 }
            ]
          },
          "unit": "percent"
        }
      },
      "gridPos": { "h": 4, "w": 4, "x": 12, "y": 1 },
      "id": 24,
      "options": {
        "reduceOptions": {
          "calcs": ["lastNotNull"],
          "fields": "",
          "values": false
        }
      },
      "targets": [
        {
          "expr": "job:http_requests_4xx:ratio5m * 100",
          "legendFormat": "4xx %",
          "refId": "A"
        }
      ],
      "title": "4xx Rate",
      "description": "4xx client error rate as a percentage. Amber >5%, red >25%.",
      "type": "stat"
    },
    {
      "datasource": { "type": "prometheus", "uid": "${datasource_prometheus}" },
      "fieldConfig": {
        "defaults": {
          "color": { "mode": "thresholds" },
          "thresholds": {
            "mode": "absolute",
            "steps": [
              { "color": "green", "value": null },
              { "color": "amber", "value": 1 },
              { "color": "red", "value": 5 }
            ]
          },
          "unit": "percent"
        }
      },
      "gridPos": { "h": 4, "w": 4, "x": 16, "y": 1 },
      "id": 3,
      "options": {
        "reduceOptions": {
          "calcs": ["lastNotNull"],
          "fields": "",
          "values": false
        }
      },
      "targets": [
        {
          "expr": "job:http_requests_errors:ratio5m * 100",
          "legendFormat": "Error %",
          "refId": "A"
        }
      ],
      "title": "Error Rate",
      "description": "5xx error rate as a percentage. Amber >1%, red >5%.",
      "type": "stat"
    },
    {
      "datasource": { "type": "prometheus", "uid": "${datasource_prometheus}" },
      "fieldConfig": {
        "defaults": {
          "color": { "mode": "thresholds" },
          "thresholds": {
            "mode": "absolute",
            "steps": [
              { "color": "green", "value": null },
              { "color": "amber", "value": 0.5 },
              { "color": "red", "value": 2 }
            ]
          },
          "unit": "s"
        }
      },
      "gridPos": { "h": 4, "w": 4, "x": 8, "y": 1 },
      "id": 4,
      "options": {
        "reduceOptions": {
          "calcs": ["lastNotNull"],
          "fields": "",
          "values": false
        }
      },
      "targets": [
        {
          "expr": "job:http_request_duration:p95_5m",
          "legendFormat": "p95",
          "refId": "A"
        }
      ],
      "title": "p95 Latency",
      "description": "95th percentile latency. Amber >0.5s, red >2s.",
      "type": "stat"
    },
    {
      "datasource": { "type": "prometheus", "uid": "${datasource_prometheus}" },
      "fieldConfig": {
        "defaults": {
          "color": { "mode": "thresholds" },
          "unit": "short"
        }
      },
      "gridPos": { "h": 4, "w": 4, "x": 20, "y": 1 },
      "id": 5,
      "options": {
        "reduceOptions": {
          "calcs": ["lastNotNull"],
          "fields": "",
          "values": false
        }
      },
      "targets": [
        {
          "expr": "sum(http_requests_in_flight)",
          "legendFormat": "In-Flight",
          "refId": "A"
        }
      ],
      "title": "In-Flight",
      "description": "Total in-flight HTTP requests across all backend instances right now.",
      "type": "stat"
    },
    {
      "datasource": { "type": "prometheus", "uid": "${datasource_prometheus}" },
      "fieldConfig": {
        "defaults": {
          "color": { "mode": "thresholds" },
          "thresholds": {
            "mode": "absolute",
            "steps": [
              { "color": "green", "value": null },
              { "color": "amber", "value": 0.25 },
              { "color": "red", "value": 1 }
            ]
          },
          "unit": "s"
        }
      },
      "gridPos": { "h": 4, "w": 4, "x": 4, "y": 1 },
      "id": 31,
      "options": {
        "reduceOptions": {
          "calcs": ["lastNotNull"],
          "fields": "",
          "values": false
        }
      },
      "targets": [
        {
          "expr": "histogram_quantile(0.50, sum(rate(http_request_duration_seconds_bucket[5m])) by (le))",
          "legendFormat": "p50",
          "refId": "A"
        }
      ],
      "title": "p50 Latency",
      "description": "50th percentile latency. Amber >0.25s, red >1s.",
      "type": "stat"
    },
    {
      "collapsed": false,
      "gridPos": { "h": 1, "w": 24, "x": 0, "y": 9 },
      "id": 6,
      "title": "Rate & Errors",
      "type": "row"
    },
    {
      "datasource": { "type": "prometheus", "uid": "${datasource_prometheus}" },
      "fieldConfig": {
        "defaults": {
          "color": { "mode": "fixed" },
          "custom": {
            "lineWidth": 1,
            "pointSize": 4,
            "showPoints": "auto"
          },
          "unit": "reqps"
        },
        "overrides": [
          {
            "matcher": { "id": "byName", "options": "2xx" },
            "properties": [
              { "id": "color", "value": { "fixedColor": "#73BF69", "mode": "fixed" } }
            ]
          },
          {
            "matcher": { "id": "byName", "options": "3xx" },
            "properties": [
              { "id": "color", "value": { "fixedColor": "#5794F2", "mode": "fixed" } }
            ]
          },
          {
            "matcher": { "id": "byName", "options": "4xx" },
            "properties": [
              { "id": "color", "value": { "fixedColor": "#EAB839", "mode": "fixed" } }
            ]
          },
          {
            "matcher": { "id": "byName", "options": "5xx" },
            "properties": [
              { "id": "color", "value": { "fixedColor": "#F2495C", "mode": "fixed" } }
            ]
          }
        ]
      },
      "gridPos": { "h": 8, "w": 12, "x": 0, "y": 10 },
      "id": 7,
      "links": [
        {
          "title": "View Logs",
          "url": "/d/graveboards-logs?var-service=backend&var-level=error&from=${__from}&to=${__to}",
          "targetBlank": false,
          "type": "link"
        }
      ],
      "targets": [
        {
          "expr": "sum(rate(http_requests_total{status_code=~\"2..\"}[5m]))",
          "legendFormat": "2xx",
          "refId": "A"
        },
        {
          "expr": "sum(rate(http_requests_total{status_code=~\"3..\"}[5m]))",
          "legendFormat": "3xx",
          "refId": "B"
        },
        {
          "expr": "sum(rate(http_requests_total{status_code=~\"4..\"}[5m]))",
          "legendFormat": "4xx",
          "refId": "C"
        },
        {
          "expr": "sum(rate(http_requests_total{status_code=~\"5..\"}[5m]))",
          "legendFormat": "5xx",
          "refId": "D"
        }
      ],
      "title": "Request Rate by Status Class",
      "description": "Request rate grouped by HTTP status class (2xx success, 3xx redirect, 4xx client error, 5xx server error).",
      "type": "timeseries"
    },
    {
      "datasource": { "type": "prometheus", "uid": "${datasource_prometheus}" },
      "fieldConfig": {
        "defaults": {
          "color": { "mode": "fixed" },
          "custom": {
            "lineWidth": 1,
            "pointSize": 4,
            "showPoints": "auto"
          },
          "thresholds": {
            "mode": "absolute",
            "steps": [
              { "color": "green", "value": null },
              { "color": "amber", "value": 1 },
              { "color": "red", "value": 5 }
            ]
          },
          "unit": "percent"
        },
        "overrides": [
          {
            "matcher": { "id": "byName", "options": "4xx %" },
            "properties": [
              { "id": "color", "value": { "fixedColor": "#EAB839", "mode": "fixed" } }
            ]
          },
          {
            "matcher": { "id": "byName", "options": "5xx %" },
            "properties": [
              { "id": "color", "value": { "fixedColor": "#F2495C", "mode": "fixed" } }
            ]
          }
        ]
      },
      "gridPos": { "h": 8, "w": 12, "x": 12, "y": 10 },
      "id": 8,
      "links": [
        {
          "title": "View Logs",
          "url": "/d/graveboards-logs?var-service=backend&var-level=error&from=${__from}&to=${__to}",
          "targetBlank": false,
          "type": "link"
        }
      ],
      "targets": [
        {
          "expr": "sum(rate(http_requests_total{status_code=~\"4..\"}[5m])) / sum(rate(http_requests_total[5m])) * 100",
          "legendFormat": "4xx %",
          "refId": "A"
        },
        {
          "expr": "sum(rate(http_requests_total{status_code=~\"5..\"}[5m])) / sum(rate(http_requests_total[5m])) * 100",
          "legendFormat": "5xx %",
          "refId": "B"
        }
      ],
      "title": "Error Ratio 4xx vs 5xx",
      "description": "4xx and 5xx error rates as a percentage of total requests. Amber >1%, red >5%.",
      "type": "timeseries"
    },
    {
      "collapsed": false,
      "gridPos": { "h": 1, "w": 24, "x": 0, "y": 18 },
      "id": 25,
      "title": "Errors",
      "type": "row"
    },
    {
      "datasource": { "type": "prometheus", "uid": "${datasource_prometheus}" },
      "fieldConfig": {
        "defaults": {
          "color": { "mode": "fixed" },
          "custom": {
            "lineWidth": 1,
            "pointSize": 4,
            "showPoints": "auto"
          },
          "unit": "short"
        },
        "overrides": [
          {
            "matcher": { "id": "byName", "options": "bad_request" },
            "properties": [
              { "id": "color", "value": { "fixedColor": "#EAB839", "mode": "fixed" } }
            ]
          },
          {
            "matcher": { "id": "byName", "options": "forbidden" },
            "properties": [
              { "id": "color", "value": { "fixedColor": "#FF9830", "mode": "fixed" } }
            ]
          },
          {
            "matcher": { "id": "byName", "options": "unauthorized" },
            "properties": [
              { "id": "color", "value": { "fixedColor": "#F2CC04", "mode": "fixed" } }
            ]
          },
          {
            "matcher": { "id": "byName", "options": "internal_server_error" },
            "properties": [
              { "id": "color", "value": { "fixedColor": "#F2495C", "mode": "fixed" } }
            ]
          }
        ]
      },
      "gridPos": { "h": 8, "w": 12, "x": 0, "y": 19 },
      "id": 26,
      "links": [
        {
          "title": "View Logs",
          "url": "/d/graveboards-logs?var-service=backend&var-level=error&from=${__from}&to=${__to}",
          "targetBlank": false,
          "type": "link"
        }
      ],
      "targets": [
        {
          "expr": "job:errors_by_type:rate5m",
          "legendFormat": "{{error_type}}",
          "refId": "A"
        }
      ],
      "title": "Error Rate by Type",
      "description": "Rate of errors grouped by error_type. Note: search_requests_total/search_duration_seconds record successful searches only; failed/invalid search requests appear here as error_type=bad_request.",
      "type": "timeseries"
    },
    {
      "datasource": { "type": "prometheus", "uid": "${datasource_prometheus}" },
      "fieldConfig": {
        "defaults": {
          "color": { "mode": "fixed" },
          "custom": {
            "align": "auto",
            "displayMode": "color-background",
            "inspect": false
          },
          "unit": "reqps"
        },
        "overrides": [
          {
            "matcher": { "id": "byName", "options": "endpoint" },
            "properties": [
              {
                "id": "links",
                "value": [
                  {
                    "title": "View logs for this endpoint",
                    "url": "/d/graveboards-logs?var-service=backend&var-logger=app.access&var-search=${__value.text}&from=${__from}&to=${__to}",
                    "targetBlank": false
                  }
                ]
              }
            ]
          },
          {
            "matcher": { "id": "byName", "options": "error_type" },
            "properties": [
              {
                "id": "custom.displayMode",
                "value": "color-text"
              }
            ]
          }
        ]
      },
      "gridPos": { "h": 8, "w": 12, "x": 12, "y": 19 },
      "id": 27,
      "links": [
        {
          "title": "View Logs",
          "url": "/d/graveboards-logs?var-service=backend&var-level=error&from=${__from}&to=${__to}",
          "targetBlank": false,
          "type": "link"
        }
      ],
      "options": {
        "showHeader": true,
        "sortBy": [
          { "desc": true, "displayName": "Rate" }
        ]
      },
      "targets": [
        {
          "expr": "topk(10, sum(rate(errors_total[5m])) by (endpoint, error_type))",
          "legendFormat": "{{endpoint}} / {{error_type}}",
          "refId": "A"
        }
      ],
      "title": "Errors by Endpoint & Type",
      "description": "Top 10 endpoint/error_type combinations by rate. Click an endpoint to view its logs.",
      "type": "table"
    },
    {
      "collapsed": false,
      "gridPos": { "h": 1, "w": 24, "x": 0, "y": 27 },
      "id": 9,
      "title": "Latency",
      "type": "row"
    },
    {
      "datasource": { "type": "prometheus", "uid": "${datasource_prometheus}" },
      "fieldConfig": {
        "defaults": {
          "color": { "mode": "fixed" },
          "custom": {
            "lineWidth": 1,
            "pointSize": 4,
            "showPoints": "auto"
          },
          "unit": "s"
        },
        "overrides": [
          {
            "matcher": { "id": "byName", "options": "p50" },
            "properties": [
              { "id": "color", "value": { "fixedColor": "#73BF69", "mode": "fixed" } }
            ]
          },
          {
            "matcher": { "id": "byName", "options": "p95" },
            "properties": [
              { "id": "color", "value": { "fixedColor": "#EAB839", "mode": "fixed" } }
            ]
          },
          {
            "matcher": { "id": "byName", "options": "p99" },
            "properties": [
              { "id": "color", "value": { "fixedColor": "#F2495C", "mode": "fixed" } }
            ]
          }
        ]
      },
      "gridPos": { "h": 8, "w": 12, "x": 0, "y": 28 },
      "id": 10,
      "links": [
        {
          "title": "View Logs",
          "url": "/d/graveboards-logs?var-service=backend&var-level=error&from=${__from}&to=${__to}",
          "targetBlank": false,
          "type": "link"
        }
      ],
      "targets": [
        {
          "expr": "histogram_quantile(0.50, sum(rate(http_request_duration_seconds_bucket[5m])) by (le))",
          "legendFormat": "p50",
          "refId": "A"
        },
        {
          "expr": "histogram_quantile(0.95, sum(rate(http_request_duration_seconds_bucket[5m])) by (le))",
          "legendFormat": "p95",
          "refId": "B"
        },
        {
          "expr": "histogram_quantile(0.99, sum(rate(http_request_duration_seconds_bucket[5m])) by (le))",
          "legendFormat": "p99",
          "refId": "C"
        }
      ],
      "title": "Latency Percentiles p50 / p95 / p99",
      "description": "50th, 95th, and 99th percentile HTTP request latency. Green = p50, amber = p95, red = p99.",
      "type": "timeseries"
    },
    {
      "datasource": { "type": "prometheus", "uid": "${datasource_prometheus}" },
      "fieldConfig": {
        "defaults": {
          "color": {
            "scheme": "hot",
            "mode": "opacity"
          },
          "custom": {
            "fillOpacity": 100,
            "lineWidth": 0,
            "gradientMode": "scheme",
            "scale": "log"
          },
          "unit": "s"
        }
      },
      "gridPos": { "h": 8, "w": 12, "x": 12, "y": 28 },
      "id": 11,
      "links": [
        {
          "title": "View Logs",
          "url": "/d/graveboards-logs?var-service=backend&var-level=error&from=${__from}&to=${__to}",
          "targetBlank": false,
          "type": "link"
        }
      ],
      "options": {
        "calculate": false,
        "cellGap": 1,
        "color": {
          "exponent": 0.5,
          "fill": "dark-orange",
          "mode": "scheme",
          "reverse": false,
          "scale": "exponential",
          "scheme": "Hot",
          "steps": 64
        },
        "exemplars": {
          "color": "rgba(255,0,255,0.7)"
        },
        "filterValues": {
          "le": 1e-9
        },
        "rowsFrame": {
          "layout": "auto"
        },
        "tooltip": {
          "mode": "single",
          "showColorScale": false,
          "yHistogram": false
        },
        "yAxis": {
          "axisPlacement": "left",
          "reverse": false,
          "unit": "s"
        }
      },
      "targets": [
        {
          "expr": "sum(increase(http_request_duration_seconds_bucket[5m])) by (le)",
          "legendFormat": "{{le}}",
          "refId": "A"
        }
      ],
      "title": "Latency Heatmap",
      "description": "Full distribution of HTTP request latencies. Darker = more requests at that duration. Useful for spotting tail latency that percentiles alone might miss.",
      "type": "heatmap"
    },
    {
      "collapsed": false,
      "gridPos": { "h": 1, "w": 24, "x": 0, "y": 36 },
      "id": 12,
      "title": "Endpoints",
      "type": "row"
    },
    {
      "datasource": { "type": "prometheus", "uid": "${datasource_prometheus}" },
      "fieldConfig": {
        "defaults": {
          "custom": {
            "align": "auto",
            "displayMode": "auto",
            "inspect": false
          }
        },
        "overrides": [
          {
            "matcher": { "id": "byName", "options": "endpoint" },
            "properties": [
              {
                "id": "links",
                "value": [
                  {
                    "title": "View logs for this endpoint",
                    "url": "/d/graveboards-logs?var-service=backend&var-logger=app.access&var-search=${__value.text}&from=${__from}&to=${__to}",
                    "targetBlank": false
                  }
                ]
              }
            ]
          }
        ]
      },
      "gridPos": { "h": 8, "w": 8, "x": 0, "y": 37 },
      "id": 13,
      "links": [
        {
          "title": "View Logs",
          "url": "/d/graveboards-logs?var-service=backend&from=${__from}&to=${__to}",
          "targetBlank": false,
          "type": "link"
        }
      ],
      "options": {
        "showHeader": true,
        "sortBy": [
          { "desc": true, "displayName": "Rate" }
        ]
      },
      "targets": [
        {
          "expr": "topk(10, sum(rate(http_requests_total[5m])) by (endpoint))",
          "legendFormat": "{{endpoint}}",
          "refId": "A"
        }
      ],
      "title": "Endpoints by Rate",
      "description": "Top 10 endpoints by request rate.",
      "type": "table"
    },
    {
      "datasource": { "type": "prometheus", "uid": "${datasource_prometheus}" },
      "fieldConfig": {
        "defaults": {
          "color": { "mode": "thresholds" },
          "custom": {
            "align": "auto",
            "displayMode": "color-background",
            "inspect": false
          },
          "thresholds": {
            "mode": "absolute",
            "steps": [
              { "color": "green", "value": null },
              { "color": "amber", "value": 1 },
              { "color": "red", "value": 5 }
            ]
          },
          "unit": "percent"
        },
        "overrides": [
          {
            "matcher": { "id": "byName", "options": "endpoint" },
            "properties": [
              {
                "id": "links",
                "value": [
                  {
                    "title": "View logs for this endpoint",
                    "url": "/d/graveboards-logs?var-service=backend&var-logger=app.access&var-search=${__value.text}&from=${__from}&to=${__to}",
                    "targetBlank": false
                  }
                ]
              },
              { "id": "custom.displayMode", "value": "auto" }
            ]
          }
        ]
      },
      "gridPos": { "h": 8, "w": 8, "x": 8, "y": 37 },
      "id": 19,
      "links": [
        {
          "title": "View Logs",
          "url": "/d/graveboards-logs?var-service=backend&var-level=error&from=${__from}&to=${__to}",
          "targetBlank": false,
          "type": "link"
        }
      ],
      "options": {
        "showHeader": true,
        "sortBy": [
          { "desc": true, "displayName": "Value" }
        ]
      },
      "targets": [
        {
          "expr": "topk(10, sum(rate(http_requests_total{status_code=~\"4..|5..\"}[5m])) by (endpoint) / sum(rate(http_requests_total[5m])) by (endpoint) * 100)",
          "legendFormat": "{{endpoint}}",
          "refId": "A"
        }
      ],
      "title": "Endpoints by Error %",
      "description": "Top 10 endpoints by 4xx/5xx error percentage.",
      "type": "table"
    },
    {
      "datasource": { "type": "prometheus", "uid": "${datasource_prometheus}" },
      "fieldConfig": {
        "defaults": {
          "custom": {
            "align": "auto",
            "displayMode": "auto",
            "inspect": false
          },
          "unit": "s"
        },
        "overrides": [
          {
            "matcher": { "id": "byName", "options": "endpoint" },
            "properties": [
              {
                "id": "links",
                "value": [
                  {
                    "title": "View logs for this endpoint",
                    "url": "/d/graveboards-logs?var-service=backend&var-logger=app.access&var-search=${__value.text}&from=${__from}&to=${__to}",
                    "targetBlank": false
                  }
                ]
              }
            ]
          }
        ]
      },
      "gridPos": { "h": 8, "w": 8, "x": 16, "y": 37 },
      "id": 20,
      "links": [
        {
          "title": "View Logs",
          "url": "/d/graveboards-logs?var-service=backend&from=${__from}&to=${__to}",
          "targetBlank": false,
          "type": "link"
        }
      ],
      "options": {
        "showHeader": true,
        "sortBy": [
          { "desc": true, "displayName": "Value" }
        ]
      },
      "targets": [
        {
          "expr": "topk(10, histogram_quantile(0.95, sum(rate(http_request_duration_seconds_bucket[5m])) by (le, endpoint)))",
          "legendFormat": "{{endpoint}}",
          "refId": "A"
        }
      ],
      "title": "Endpoints by p95 Latency",
      "description": "Top 10 endpoints by 95th percentile latency.",
      "type": "table"
    },
    {
      "collapsed": false,
      "gridPos": { "h": 1, "w": 24, "x": 0, "y": 45 },
      "id": 28,
      "title": "Auth Rate Limiting",
      "type": "row"
    },
    {
      "datasource": { "type": "prometheus", "uid": "${datasource_prometheus}" },
      "fieldConfig": {
        "defaults": {
          "color": { "mode": "palette-classic" },
          "custom": {
            "lineWidth": 1,
            "pointSize": 4,
            "showPoints": "auto"
          },
          "unit": "ops"
        },
        "overrides": [
          {
            "matcher": { "id": "byName", "options": "allowed" },
            "properties": [
              { "id": "color", "value": { "fixedColor": "#73BF69", "mode": "fixed" } }
            ]
          },
          {
            "matcher": { "id": "byName", "options": "rate_limited" },
            "properties": [
              { "id": "color", "value": { "fixedColor": "#EAB839", "mode": "fixed" } }
            ]
          },
          {
            "matcher": { "id": "byName", "options": "locked_out" },
            "properties": [
              { "id": "color", "value": { "fixedColor": "#F2495C", "mode": "fixed" } }
            ]
          }
        ]
      },
      "gridPos": { "h": 8, "w": 12, "x": 0, "y": 46 },
      "id": 29,
      "links": [
        {
          "title": "View Logs",
          "url": "/d/graveboards-logs?var-service=backend&var-level=error&from=${__from}&to=${__to}",
          "targetBlank": false,
          "type": "link"
        }
      ],
      "targets": [
        {
          "expr": "sum(rate(auth_rate_limit_checks_total[5m])) by (result)",
          "legendFormat": "{{result}}",
          "refId": "A"
        }
      ],
      "title": "Auth Check Results",
      "description": "Inbound auth rate-limit check outcomes. Measures brute-force/credential-stuffing protection on /login and /token.",
      "type": "timeseries"
    },
    {
      "datasource": { "type": "prometheus", "uid": "${datasource_prometheus}" },
      "fieldConfig": {
        "defaults": {
          "color": { "mode": "thresholds" },
          "thresholds": {
            "mode": "absolute",
            "steps": [
              { "color": "green", "value": null },
              { "color": "amber", "value": 1 },
              { "color": "red", "value": 5 }
            ]
          },
          "unit": "ops"
        }
      },
      "gridPos": { "h": 8, "w": 12, "x": 12, "y": 46 },
      "id": 30,
      "links": [
        {
          "title": "View Logs",
          "url": "/d/graveboards-logs?var-service=backend&var-level=error&from=${__from}&to=${__to}",
          "targetBlank": false,
          "type": "link"
        }
      ],
      "targets": [
        {
          "expr": "job:auth_rate_limit:lockout_rate5m",
          "legendFormat": "Lockout rate",
          "refId": "A"
        }
      ],
      "title": "Lockouts",
      "description": "Rate of IP lockouts for excessive auth failures. Amber >1/s, red >5/s.",
      "type": "stat"
    },
    {
      "collapsed": false,
      "gridPos": { "h": 1, "w": 24, "x": 0, "y": 54 },
      "id": 21,
      "title": "API Requests",
      "type": "row"
    },
    {
      "datasource": { "type": "loki", "uid": "${datasource_loki}" },
      "fieldConfig": {
        "defaults": {
          "color": { "mode": "palette-classic" }
        }
      },
      "gridPos": { "h": 10, "w": 8, "x": 0, "y": 55 },
      "id": 22,
      "options": {
        "orientation": "horizontal",
        "showThresholdLabels": false,
        "showThresholdMarkers": false,
        "reduceOptions": {
          "calcs": ["sum"],
          "fields": "",
          "values": false
        }
      },
      "targets": [
        {
          "expr": "sum by (auth_scheme) (count_over_time({service=~\"$service\"} | json | logger=\"app.access\" | user_id=~\"$user_id\" [$__range]))",
          "legendFormat": "{{auth_scheme}}",
          "refId": "A"
        }
      ],
      "title": "Requests by Auth Type",
      "description": "Who's calling the API: bearer (JWT user), api_key, or none (guest/unauthenticated). Grouped by the `auth_scheme` JSON field emitted by app.access.",
      "type": "bargauge"
    },
    {
      "datasource": { "type": "loki", "uid": "${datasource_loki}" },
      "gridPos": { "h": 10, "w": 16, "x": 8, "y": 55 },
      "id": 23,
      "options": {
        "dedupStrategy": "none",
        "enableLogDetails": true,
        "prettifyLogMessage": true,
        "showTime": true,
        "showLabels": false,
        "showCommonLabels": false,
        "enableLogDetailsOpenClose": true,
        "wrapLogMessage": true,
        "sortOrder": "Descending",
        "timestampFormat": "2006-01-02 15:04:05"
      },
      "targets": [
        {
          "expr": "{service=~\"$service\"} | json | logger=\"app.access\" | user_id=~\"$user_id\" |= \"$search\"",
          "legendFormat": "",
          "refId": "A"
        }
      ],
      "title": "API Request Stream",
      "description": "Every app.access line, filtered to just this logger. Expand a row's Log details to see the full parsed request: query_params, body (redacted, JSON/form bodies ≤ 8KB only), user_id, and auth_scheme, alongside the existing method/path/status/duration summary. Filter to one caller with the User ID variable above.",
      "type": "logs"
    }
  ],
  "refresh": "30s",
  "schemaVersion": 39,
  "style": "dark",
  "tags": ["graveboards", "api"],
  "templating": {
    "list": [
      {
        "current": {},
        "hide": 0,
        "includeAll": false,
        "label": "Prometheus",
        "multi": false,
        "name": "datasource_prometheus",
        "options": [],
        "query": "prometheus",
        "refresh": 1,
        "regex": "",
        "skipUrlSync": false,
        "type": "datasource"
      },
      {
        "current": {},
        "hide": 0,
        "includeAll": false,
        "label": "Loki",
        "multi": false,
        "name": "datasource_loki",
        "options": [],
        "query": "loki",
        "refresh": 1,
        "regex": "",
        "skipUrlSync": false,
        "type": "datasource"
      },
      {
        "current": { "selected": false, "text": "backend", "value": "backend" },
        "hide": 0,
        "includeAll": true,
        "label": "Service",
        "multi": true,
        "name": "service",
        "options": [],
        "query": "label_values(service)",
        "refresh": 1,
        "regex": "",
        "skipUrlSync": false,
        "sort": 1,
        "type": "query",
        "datasource": { "type": "loki", "uid": "${datasource_loki}" }
      },
      {
        "current": { "selected": false, "text": "All", "value": ["__all"] },
        "hide": 0,
        "includeAll": true,
        "label": "Level",
        "multi": true,
        "name": "level",
        "options": [
          { "selected": false, "text": "debug", "value": "debug" },
          { "selected": false, "text": "info", "value": "info" },
          { "selected": false, "text": "warning", "value": "warning" },
          { "selected": false, "text": "error", "value": "error" },
          { "selected": false, "text": "critical", "value": "critical" }
        ],
        "query": "debug,info,warning,error,critical",
        "skipUrlSync": false,
        "type": "custom"
      },
      {
        "current": { "selected": false, "text": ".*", "value": ".*" },
        "hide": 0,
        "label": "Logger",
        "name": "logger",
        "options": [],
        "query": ".*",
        "skipUrlSync": false,
        "type": "textbox"
      },
      {
        "current": { "selected": false, "text": "", "value": "" },
        "hide": 0,
        "label": "Search",
        "name": "search",
        "options": [],
        "query": "",
        "skipUrlSync": false,
        "type": "textbox"
      },
      {
        "current": { "selected": false, "text": "", "value": "" },
        "hide": 0,
        "label": "Request ID",
        "name": "request_id",
        "options": [],
        "query": "",
        "skipUrlSync": false,
        "type": "textbox"
      },
      {
        "current": { "selected": false, "text": ".*", "value": ".*" },
        "hide": 0,
        "label": "User ID",
        "description": "Filter app.access lines to one caller. Leave as .* for everyone; an empty auth_scheme=\"none\" request logs user_id as the JSON null (matched as an empty string).",
        "name": "user_id",
        "options": [],
        "query": ".*",
        "skipUrlSync": false,
        "type": "textbox"
      }
    ]
  },
  "time": { "from": "now-6h", "to": "now" },
  "timepicker": {},
  "timezone": "",
  "title": "API & Requests",
  "uid": "graveboards-api",
  "version": 2
}
